wrapper/__init__.py
wrapper/ai.py
SoapAIWrapper-0.2.5.dist-info/METADATA
SoapAIWrapper-0.2.5.dist-info/WHEEL
SoapAIWrapper-0.2.5.dist-info/top_level.txt
SoapAIWrapper-0.2.5.dist-info/RECORD
