Metadata-Version: 2.1
Name: SoapAIWrapper
Version: 0.2.5
Summary: My personal OpenAI Wrapper
Home-page: https://github.com/Mrmii321/soapAiWrapper
Author: soapchan
Author-email: noahfoxgaming@gmail.com
License: MIT
Requires-Dist: openai
